ds_toolkit/__init__.py
ds_toolkit/avl.py
ds_toolkit/bst.py
ds_toolkit/doubly_linked_list.py
ds_toolkit/heap.py
ds_toolkit/queue.py
ds_toolkit/singly_linked_list.py
ds_toolkit/stack.py
ds_toolkit/union_find.py
toolkit_ds-0.1.1.dist-info/LICENSE
toolkit_ds-0.1.1.dist-info/METADATA
toolkit_ds-0.1.1.dist-info/WHEEL
toolkit_ds-0.1.1.dist-info/top_level.txt
toolkit_ds-0.1.1.dist-info/RECORD
