Metadata-Version: 2.1
Name: toolkit_ds
Version: 0.1.1
Summary: A Python package implementing core data structures and algorithms.
Home-page: https://github.com/ARAVIND281/ds_toolkit
Author: Aravind S
Author-email: aravind@inbo.tech
Classifier: Programming Language :: Python :: 3
Classifier: License :: OSI Approved :: MIT License
Classifier: Operating System :: OS Independent
Requires-Python: >=3.7
License-File: LICENSE
